legrad/__init__.py
legrad/utils.py
legrad/wrapper.py
legrad_torch-1.1.dist-info/LICENSE
legrad_torch-1.1.dist-info/METADATA
legrad_torch-1.1.dist-info/WHEEL
legrad_torch-1.1.dist-info/top_level.txt
legrad_torch-1.1.dist-info/RECORD
