Metadata-Version: 2.1
Name: legrad-torch
Version: 1.1
Summary: LeGrad
Home-page: https://github.com/WalBouss/LeGrad
Author: Walid Bousselham, Angie Boggust, Sofian Chaybouti, Hendrik Strobelt, Hilde Kuehne
Author-email: 
Keywords: Explainability,ViT,Vision-Language Models,GradCAM,CLIP pretrained
Classifier: Development Status :: 3 - Alpha
Classifier: Intended Audience :: Education
Classifier: Intended Audience :: Science/Research
Classifier: License :: OSI Approved :: Apache Software License
Classifier: Programming Language :: Python :: 3.7
Classifier: Programming Language :: Python :: 3.8
Classifier: Programming Language :: Python :: 3.9
Classifier: Programming Language :: Python :: 3.10
Classifier: Topic :: Scientific/Engineering
Classifier: Topic :: Scientific/Engineering :: Artificial Intelligence
Classifier: Topic :: Software Development
Classifier: Topic :: Software Development :: Libraries
Classifier: Topic :: Software Development :: Libraries :: Python Modules
Requires-Python: >=3.7
License-File: LICENSE
Requires-Dist: torch >=1.11
Requires-Dist: torchvision
Requires-Dist: timm
Requires-Dist: open-clip-torch <=2.23.0
Requires-Dist: opencv-python
Requires-Dist: matplotlib
Requires-Dist: numpy
Requires-Dist: requests
Requires-Dist: einops
